rules_validations/__init__.py
rules_validations/baseEnum.py
rules_validations/normalize.py
rules_validations-0.6.5.dist-info/METADATA
rules_validations-0.6.5.dist-info/WHEEL
rules_validations-0.6.5.dist-info/RECORD
