Metadata-Version: 2.1
Name: rules-validations
Version: 0.6.5
Summary: 
Author: Gianfranco Cossani
Author-email: gianfranco.cossani@applydigital.com
Requires-Python: >=3.10,<4.0
Classifier: Programming Language :: Python :: 3
Classifier: Programming Language :: Python :: 3.10
Classifier: Programming Language :: Python :: 3.11
Requires-Dist: jinja2 (>=3.1.2,<4.0.0)
Requires-Dist: pydantic (>=2.0.2,<3.0.0)
